Bytum_RM/__init__.py
Bytum_RM-1.0.0a0.dist-info/METADATA
Bytum_RM-1.0.0a0.dist-info/WHEEL
Bytum_RM-1.0.0a0.dist-info/top_level.txt
Bytum_RM-1.0.0a0.dist-info/RECORD
