Metadata-Version: 2.1
Name: Bytum-RM
Version: 1.0.0a0
Summary: The ReMake edition of Bytum,it was made by the same Author,but the name has changed.
Home-page: UNKNOWN
Author: TunaFish2K
Author-email: tunafish2k@lieyan.space
License: UNKNOWN
Platform: UNKNOWN
